distvae_tabular/__init__.py
distvae_tabular/dataset.py
distvae_tabular/distvae.py
distvae_tabular/model.py
distvae_tabular-0.2.4.dist-info/METADATA
distvae_tabular-0.2.4.dist-info/WHEEL
distvae_tabular-0.2.4.dist-info/top_level.txt
distvae_tabular-0.2.4.dist-info/RECORD
