Metadata-Version: 2.1
Name: distvae_tabular
Version: 0.2.4
Summary: Package for Synthetic Data Generation using Distributional Learninig of VAE
Home-page: https://github.com/an-seunghwan/DistVAE-Tabular
Author: Seunghwan An
Author-email: dpeltms79@gmail.com
Classifier: Programming Language :: Python :: 3
Requires-Python: >=3.11
Requires-Dist: numpy==1.26.4
Requires-Dist: pandas==2.2.2
Requires-Dist: scikit-learn==1.5.1
Requires-Dist: scipy==1.14.0
Requires-Dist: torch==2.2.2
Requires-Dist: tqdm==4.66.4
